descarga_datos/__init__.py
descarga_datos/app.py
descarga_datos/cli.py
descarga_datos/internals/Analysis.py
descarga_datos/internals/DataFile.py
descarga_datos/internals/__init__.py
descarga_datos/internals/setup_data.py
descarga_datos/network/__init__.py
descarga_datos/network/get_data.py
descarga_datos/utils/__init__.py
descarga_datos/utils/enviroment.py
descarga_datos-0.4.5.dist-info/entry_points.txt
descarga_datos-0.4.5.dist-info/licenses/LICENSE
descarga_datos-0.4.5.dist-info/WHEEL
descarga_datos-0.4.5.dist-info/METADATA
descarga_datos-0.4.5.dist-info/RECORD
