Metadata-Version: 2.4
Name: descarga_datos
Version: 0.4.5
Summary: A local Python module
Home-page: https://github.com/IslasGECI/descarga_datos
Author: Ciencia de Datos • GECI
Author-email: ciencia.datos@islas.org.mx
Requires-Python: >=3.8
Classifier: License :: OSI Approved :: GNU General Public License v3 or later (GPLv3+)
License-File: LICENSE
Requires-Dist: pandas
Requires-Dist: requests
Requires-Dist: typer[all]
